aetos.py
aetos_wrapper-1.0.0.dist-info/METADATA
aetos_wrapper-1.0.0.dist-info/WHEEL
aetos_wrapper-1.0.0.dist-info/entry_points.txt
aetos_wrapper-1.0.0.dist-info/top_level.txt
aetos_wrapper-1.0.0.dist-info/RECORD
