Metadata-Version: 2.4
Name: aetos-wrapper
Version: 1.0.0
Summary: 🦅 Un wrapper de pip que usa un servidor de paquetes personalizado (preconfigurado)
Author-email: Johny Yen <johny.yen@example.com>
License: MIT
Project-URL: Homepage, https://github.com/JohnyYen/aetos
Project-URL: Repository, https://github.com/JohnyYen/aetos
Keywords: pip,wrapper,package manager,pypi,mirror,registry
Classifier: Programming Language :: Python :: 3
Classifier: License :: OSI Approved :: MIT License
Classifier: Operating System :: OS Independent
Requires-Python: >=3.7
